{
    "provenance": "Alexander Turney Stewart (1802\u20131876), New York; by inheritance to his wife, Cornelia Mitchell Clinch Stewart (1802\u20131886), New York, 1876 [see note 1]; sale, American Art Association, 23\u201325 March, 1887, lot 996 [see note 2]. Charles Magnell (1932\u2013 1996), Saratoga Springs, N.Y., by 1987 [see note 3]; sold to Meg Caldwell, New York, 1987; sale, Doyle, New York, May 2, 2023, lot 321; sold to Stewart Rosenblum, New York, May 2, 2023; given to the Yale University Art Gallery, New Haven, Conn., 2023\r\n\r\nNote 1: A.T. Stewart\u2019s will, dated April 30, 1876, states \u201cAll my property and estates of any and every kind and description, and wherever situated, I give, devise, and bequeath to my dear wife, Cornelia M. Stewart\u201d (copy in curatorial object file).  \r\n\r\nNote 2: Collection sold at the direction of Mrs. Stewart\u2019s executors, Henry Hilton and Charles Clinch. Lot 996 described as \u201cLarge center table, carved rosewood and gilt, marquetry top, with repouss\u00e9 bronze rim, decorated porcelain medallions and ormolou mountings\u201d (American Art Association, The Stewart Collection of Paintings, Sculpture, and Other Objects of Art, March 23\u201325, 1887, copy in curatorial object file).\r\n\r\nNote 3: According to Magnell, he acquired the table from a member of the Hilton family in the Saratoga Springs area. In addition to being executor for both A. T. and Cornelia Stewart, Hilton shared business interests with the Stewarts and both families had properties in Saratoga Springs. Newspaper accounts record that the Hilton family bought numerous lots at the Stewart auction although records for the furniture portion are vague. Magnell presumed that Hilton purchased the table and it remained in the family (copies of notes from the previous owner and copies of period news accounts in curatorial object file).",
    "output": [
        {
            "movements": [
                {
                    "source": "Unknown",
                    "target": {
                        "name": "Alexander Turney Stewart",
                        "location": "New York",
                        "birth_date": "1802",
                        "death_date": "1876",
                        "type": "Collector"
                    },
                    "start_time": "Unknown",
                    "end_time": "1876",
                    "location": "New York",
                    "confidence": "Certain",
                    "method": "purchased by/acquired by (from/through/in)",
                    "change_in_ownership": "Unknown",
                    "change_in_location": "Unknown",
                    "change_in_custody": "Unknown"
                },
                {
                    "source": {
                        "name": "Alexander Turney Stewart",
                        "location": "New York",
                        "birth_date": "1802",
                        "death_date": "1876",
                        "type": "Collector"
                    },
                    "target": {
                        "name": "Cornelia Mitchell Clinch Stewart",
                        "location": "New York",
                        "birth_date": "1802",
                        "death_date": "1886",
                        "type": "Collector"
                    },
                    "start_time": "1876",
                    "end_time": "1886",
                    "location": "New York",
                    "confidence": "Certain",
                    "method": "by inheritance to",
                    "change_in_ownership": true,
                    "change_in_location": false,
                    "change_in_custody": true
                },
                {
                    "source": {
                        "name": "Executors of Cornelia Stewart's Estate",
                        "location": "Unknown",
                        "birth_date": "Unknown",
                        "death_date": "Unknown",
                        "type": "Group"
                    },
                    "target": {
                        "name": "American Art Association",
                        "location": "New York",
                        "birth_date": "Unknown",
                        "death_date": "Unknown",
                        "type": "Institution"
                    },
                    "start_time": "1886",
                    "end_time": "1887-03-23",
                    "location": "New York",
                    "confidence": "Certain",
                    "method": "consigned to",
                    "change_in_ownership": false,
                    "change_in_location": true,
                    "change_in_custody": true
                },
                {
                    "source": {
                        "name": "American Art Association",
                        "location": "New York",
                        "birth_date": "Unknown",
                        "death_date": "Unknown",
                        "type": "Institution"
                    },
                    "target": {
                        "name": "Unknown",
                        "location": "Unknown",
                        "birth_date": "Unknown",
                        "death_date": "Unknown",
                        "type": "Unknown"
                    },
                    "start_time": "1887-03-23",
                    "end_time": "1887-03-25",
                    "location": "New York",
                    "confidence": "Certain",
                    "method": "sale",
                    "change_in_ownership": true,
                    "change_in_location": "Unknown",
                    "change_in_custody": true
                },
                {
                    "source": {
                        "name": "Unknown",
                        "location": "Unknown",
                        "birth_date": "Unknown",
                        "death_date": "Unknown",
                        "type": "Unknown"
                    },
                    "target": {
                        "name": "Charles Magnell",
                        "location": "Saratoga Springs, N.Y.",
                        "birth_date": "1932",
                        "death_date": "1996",
                        "type": "Collector"
                    },
                    "start_time": "1887-03-25",
                    "end_time": "1987",
                    "location": "Saratoga Springs, N.Y.",
                    "confidence": "Certain",
                    "method": "purchased by/acquired by (from/through/in)",
                    "change_in_ownership": true,
                    "change_in_location": true,
                    "change_in_custody": true
                },
                {
                    "source": {
                        "name": "Charles Magnell",
                        "location": "Saratoga Springs, N.Y.",
                        "birth_date": "1932",
                        "death_date": "1996",
                        "type": "Collector"
                    },
                    "target": {
                        "name": "Meg Caldwell",
                        "location": "New York",
                        "birth_date": "Unknown",
                        "death_date": "Unknown",
                        "type": "Collector"
                    },
                    "start_time": "1987",
                    "end_time": "1987",
                    "location": "New York",
                    "confidence": "Certain",
                    "method": "sold to",
                    "change_in_ownership": true,
                    "change_in_location": true,
                    "change_in_custody": true
                },
                {
                    "source": {
                        "name": "Meg Caldwell",
                        "location": "New York",
                        "birth_date": "Unknown",
                        "death_date": "Unknown",
                        "type": "Collector"
                    },
                    "target": {
                        "name": "Doyle",
                        "location": "New York",
                        "birth_date": "Unknown",
                        "death_date": "Unknown",
                        "type": "Institution"
                    },
                    "start_time": "Unknown",
                    "end_time": "2023-05-02",
                    "location": "New York",
                    "confidence": "Certain",
                    "method": "consigned to",
                    "change_in_ownership": false,
                    "change_in_location": true,
                    "change_in_custody": true
                },
                {
                    "source": {
                        "name": "Doyle",
                        "location": "New York",
                        "birth_date": "Unknown",
                        "death_date": "Unknown",
                        "type": "Institution"
                    },
                    "target": {
                        "name": "Stewart Rosenblum",
                        "location": "New York",
                        "birth_date": "Unknown",
                        "death_date": "Unknown",
                        "type": "Collector"
                    },
                    "start_time": "2023-05-02",
                    "end_time": "2023-05-02",
                    "location": "New York",
                    "confidence": "Certain",
                    "method": "sale",
                    "change_in_ownership": true,
                    "change_in_location": false,
                    "change_in_custody": true
                },
                {
                    "source": {
                        "name": "Stewart Rosenblum",
                        "location": "New York",
                        "birth_date": "Unknown",
                        "death_date": "Unknown",
                        "type": "Collector"
                    },
                    "target": {
                        "name": "Yale University Art Gallery",
                        "location": "New Haven, Conn.",
                        "birth_date": "Unknown",
                        "death_date": "Unknown",
                        "type": "Institution"
                    },
                    "start_time": "2023",
                    "end_time": "2023",
                    "location": "New Haven, Conn.",
                    "confidence": "Certain",
                    "method": "given to",
                    "change_in_ownership": true,
                    "change_in_location": true,
                    "change_in_custody": true
                }
            ],
            "model": "google/gemini-2.5-pro-preview-03-25"
        }
    ],
    "object_id": 324615,
    "errors": {},
    "date": "2025-04-29 14:35:10"
}